kubemind_common/__init__.py
kubemind_common/constants.py
kubemind_common/exceptions.py
kubemind_common/py.typed
kubemind_common/api/pagination.py
kubemind_common/cache/__init__.py
kubemind_common/cache/decorators.py
kubemind_common/cache/manager.py
kubemind_common/cache/serializers.py
kubemind_common/celery/app.py
kubemind_common/celery/health.py
kubemind_common/config/base.py
kubemind_common/contracts/actions.py
kubemind_common/contracts/alerts.py
kubemind_common/contracts/clusters.py
kubemind_common/contracts/common.py
kubemind_common/contracts/events.py
kubemind_common/contracts/executions.py
kubemind_common/contracts/investigations.py
kubemind_common/contracts/notifications.py
kubemind_common/contracts/playbooks.py
kubemind_common/contracts/triggers.py
kubemind_common/contracts/webhooks.py
kubemind_common/db/engine.py
kubemind_common/db/health.py
kubemind_common/db/models.py
kubemind_common/db/query.py
kubemind_common/errors/codes.py
kubemind_common/errors/schemas.py
kubemind_common/flags/feature_flags.py
kubemind_common/http/client.py
kubemind_common/jobs/__init__.py
kubemind_common/jobs/base.py
kubemind_common/k8s/__init__.py
kubemind_common/k8s/client.py
kubemind_common/k8s/watchers.py
kubemind_common/logging/redaction.py
kubemind_common/logging/setup.py
kubemind_common/metrics/core.py
kubemind_common/metrics/tasks.py
kubemind_common/middleware/error_handler.py
kubemind_common/middleware/rate_limit.py
kubemind_common/middleware/request_id.py
kubemind_common/middleware/request_logging.py
kubemind_common/otel/setup.py
kubemind_common/redis/client.py
kubemind_common/redis/locks.py
kubemind_common/resilience/__init__.py
kubemind_common/resilience/circuit_breaker.py
kubemind_common/resilience/retry.py
kubemind_common/security/api_keys.py
kubemind_common/security/auth.py
kubemind_common/security/hmac.py
kubemind_common/security/jwt.py
kubemind_common/security/rbac.py
kubemind_common/testing/contracts.py
kubemind_common/utils/ids.py
kubemind_common/utils/jinja.py
kubemind_common-0.1.0.dist-info/METADATA
kubemind_common-0.1.0.dist-info/WHEEL
kubemind_common-0.1.0.dist-info/licenses/LICENSE
kubemind_common-0.1.0.dist-info/RECORD
