Metadata-Version: 2.4
Name: kubemind-common
Version: 0.1.0
Summary: Shared utilities, contracts, and middleware for KubeMind services
Project-URL: Homepage, https://github.com/kubemind-ai/kubemind-common
Project-URL: Repository, https://github.com/kubemind-ai/kubemind-common.git
Author: KubeMind Team
License: MIT License
License-File: LICENSE
Keywords: kubemind,kubernetes,microservices,pydantic,utils
Classifier: Intended Audience :: Developers
Classifier: Programming Language :: Python :: 3
Classifier: Programming Language :: Python :: 3 :: Only
Classifier: Programming Language :: Python :: 3.12
Classifier: Topic :: Software Development :: Libraries
Classifier: Typing :: Typed
Requires-Python: >=3.12
Requires-Dist: httpx<0.28.0,>=0.27.2
Requires-Dist: jinja2<4.0.0,>=3.1.4
Requires-Dist: prometheus-client<0.22.0,>=0.21.0
Requires-Dist: pydantic-settings<3.0.0,>=2.6.0
Requires-Dist: pydantic<3.0.0,>=2.9.2
Requires-Dist: redis<6.0.0,>=5.2.0
Requires-Dist: tenacity<10.0.0,>=9.0.0
Provides-Extra: auth
Requires-Dist: python-jose[cryptography]<4.0.0,>=3.3.0; extra == 'auth'
Provides-Extra: celery
Requires-Dist: celery<6.0.0,>=5.3.0; extra == 'celery'
Provides-Extra: db
Requires-Dist: asyncpg<1.0.0,>=0.29.0; extra == 'db'
Requires-Dist: sqlalchemy<3.0.0,>=2.0.0; extra == 'db'
Provides-Extra: dev
Requires-Dist: build<2.0.0,>=1.2.1; extra == 'dev'
Requires-Dist: pytest-asyncio<1.0.0,>=0.24.0; extra == 'dev'
Requires-Dist: pytest<9.0.0,>=8.3.3; extra == 'dev'
Requires-Dist: requests<3.0.0,>=2.32.3; extra == 'dev'
Requires-Dist: twine<6.0.0,>=5.1.1; extra == 'dev'
Provides-Extra: fastapi
Requires-Dist: fastapi<1.0.0,>=0.115.0; extra == 'fastapi'
Requires-Dist: starlette<1.0.0,>=0.40.0; extra == 'fastapi'
Provides-Extra: otel
Requires-Dist: opentelemetry-api<2.0.0,>=1.25.0; extra == 'otel'
Requires-Dist: opentelemetry-instrumentation<1.0.0,>=0.46b0; extra == 'otel'
Requires-Dist: opentelemetry-sdk<2.0.0,>=1.25.0; extra == 'otel'
